setuptools_generate/__init__.py
setuptools_generate/_click.py
setuptools_generate/_help2man.py
setuptools_generate/_markdown_it.py
setuptools_generate/_shtab.py
setuptools_generate/_version.py
setuptools_generate/metainfo.py
setuptools_generate/py.typed
setuptools_generate/utils.py
setuptools_generate/assets/jinja2/metainfo.py.j2
setuptools_generate-0.0.6.dist-info/LICENSE
setuptools_generate-0.0.6.dist-info/METADATA
setuptools_generate-0.0.6.dist-info/WHEEL
setuptools_generate-0.0.6.dist-info/entry_points.txt
setuptools_generate-0.0.6.dist-info/top_level.txt
setuptools_generate-0.0.6.dist-info/RECORD
