Metadata-Version: 2.1
Name: setuptools-generate
Version: 0.0.6
Summary: Generate shell completions and man page when building a python package.
Author-email: Wu Zhenyu <wuzhenyu@ustc.edu>
License: GPL v3
Project-URL: Homepage, https://setuptools-generate.readthedocs.io
Project-URL: Download, https://github.com/Freed-Wu/setuptools-generate/releases
Project-URL: Bug Report, https://github.com/Freed-Wu/setuptools-generate/issues
Project-URL: Source, https://github.com/Freed-Wu/setuptools-generate
Keywords: shell completion,man,build,setuptools
Classifier: Development Status :: 3 - Alpha
Classifier: Intended Audience :: Developers
Classifier: Topic :: Software Development :: Build Tools
Classifier: License :: OSI Approved :: GNU General Public License v3 (GPLv3)
Classifier: Operating System :: Microsoft :: Windows
Classifier: Operating System :: POSIX
Classifier: Operating System :: Unix
Classifier: Operating System :: MacOS
Classifier: Programming Language :: Python :: 3 :: Only
Classifier: Programming Language :: Python :: 3
Classifier: Programming Language :: Python :: 3.9
Classifier: Programming Language :: Python :: 3.10
Classifier: Programming Language :: Python :: 3.11
Requires-Python: >=3.9
License-File: LICENSE
Requires-Dist: click
Requires-Dist: help2man
Requires-Dist: markdown-it-py
Requires-Dist: setuptools
Requires-Dist: shtab
Requires-Dist: tomli (>=1.0.0) ; python_version < "3.11"
Provides-Extra: dev
Requires-Dist: pre-commit ; extra == 'dev'
Requires-Dist: pytest-cov ; extra == 'dev'
Requires-Dist: tomli ; extra == 'dev'
